tasak/__init__.py
tasak/admin_commands.py
tasak/app_runner.py
tasak/auth.py
tasak/config.py
tasak/create_command.py
tasak/curated_app.py
tasak/docs_app.py
tasak/dynamic_registration.py
tasak/init_command.py
tasak/main.py
tasak/mcp_client.py
tasak/mcp_interactive.py
tasak/mcp_parser.py
tasak/mcp_real_client.py
tasak/mcp_remote_auth.py
tasak/mcp_remote_client.py
tasak/mcp_remote_pool.py
tasak/mcp_remote_runner.py
tasak/oauth_discovery.py
tasak/pkce.py
tasak/python_plugins.py
tasak/schema_manager.py
tasak/core/__init__.py
tasak/core/config.py
tasak/core/connection_manager.py
tasak/core/tool_service.py
tasak/core/transports/base.py
tasak/core/transports/mcp_remote.py
tasak/daemon/__init__.py
tasak/daemon/client.py
tasak/daemon/manager.py
tasak/daemon/server.py
tasak-0.1.4.dist-info/licenses/LICENSE
tasak-0.1.4.dist-info/METADATA
tasak-0.1.4.dist-info/WHEEL
tasak-0.1.4.dist-info/entry_points.txt
tasak-0.1.4.dist-info/top_level.txt
tasak-0.1.4.dist-info/RECORD
