Metadata-Version: 2.4
Name: tasak
Version: 0.1.4
Summary: Transform your AI coding assistant into a productivity powerhouse with custom tools and workflows
Author-email: Jacek Jursza <okhan.pl@gmail.com>
License: MIT License
Project-URL: Homepage, https://github.com/jacekjursza/tasak
Project-URL: Bug Tracker, https://github.com/jacekjursza/tasak/issues
Keywords: ai-agents,claude-code,cursor,copilot,developer-tools,automation,cli,mcp
Classifier: Development Status :: 4 - Beta
Classifier: Intended Audience :: Developers
Classifier: Topic :: Software Development :: Build Tools
Classifier: Topic :: Software Development :: Libraries :: Python Modules
Classifier: Topic :: System :: Shells
Classifier: License :: OSI Approved :: MIT License
Classifier: Programming Language :: Python :: 3
Classifier: Programming Language :: Python :: 3.11
Classifier: Programming Language :: Python :: 3.12
Classifier: Operating System :: OS Independent
Classifier: Environment :: Console
Requires-Python: >=3.11
License-File: LICENSE
Requires-Dist: PyYAML==6.0.1
Requires-Dist: requests
Requires-Dist: mcp>=1.13.1
Dynamic: license-file
